<layer name="CompressPackageGuideDlg" width="426" height="226" appwin="0" ncRect="0,0,0,0" resize="0" translucent="1" nomaxsize="1">
  <body>
    <dlg pos="0,0,-0,-0" class="cls_dlg_frame">
      <!--标题栏-->
      <caption pos="0,0,-0,38">
        <img pos="10,8" skin="common_logo_main"/>
        <text name="txt_title" pos="39,9" class="cls_dlg_title_text">%str830%</text>
        <imgbtn name="btn_close" skin="btn_sys_close" pos="-34,1,-2,21" cursor="arrow" tip="%str250%" animate="1"/>
      </caption>
      
      <dlg pos="0,37,-0,-0">
        <img pos="60,35,@60,@40" name="img_guide" skin="compresspackage_guide_image"/>
        <text name="txt_content" pos="144,46" crtext="03081A " font="0300:微软雅黑">%str3775%</text>
        <text name="txt_content2" pos="144,72" crtext="03081A " font="0300:微软雅黑" show="0">%str3775%</text>
        
        <imgbtn name="open_member_btn" pos="30,104,@176,@48" class="compresspackage_guide_btn_text" txtxoffset="36" txtyoffset="0" skin="btn_vip_round_angle">%str751%</imgbtn>
        <text name="member_price" pos="136,121" class="compresspackage_guide_price_text">%str3778%</text>
        
        <imgbtn name="open_unzip_btn" pos="220,104,@176,@48" class="compresspackage_guide_btn_text" txtxoffset="40" txtyoffset="0" skin="btn_default_round_angle">%str3777%</imgbtn>
        <text name="unzip_price" pos="320,121" class="compresspackage_guide_price_text">%str3780%</text>
      </dlg>
      
      <dlg name="thirdWebFramePanel" pos="0,0,-0,-0"  show="0">      
        <webbrowser name="thirdWebFrame" pos="0,0,-0,-0" use_ie="0" show="1"/> 
      </dlg>
    </dlg>
  </body>
</layer>